MANIFEST.in
README.md
setup.py
yoqle/__init__.py
yoqle/__main__.py
yoqle/script.sh
yoqle/yoqle.py
yoqle.egg-info/PKG-INFO
yoqle.egg-info/SOURCES.txt
yoqle.egg-info/dependency_links.txt
yoqle.egg-info/entry_points.txt
yoqle.egg-info/requires.txt
yoqle.egg-info/top_level.txt
yoqle/scripts/uninstall.sh
yoqle/system/create.py
yoqle/system/install.py
yoqle/system/system.py