Metadata-Version: 1.0
Name: yoqle
Version: 0.0.6
Summary: Command-line development streamlining tool.
Home-page: https://github.com/CTC97/yoqle
Author: Connor Curnin
Author-email: curnin@wisc.edu
License: UNKNOWN
Platform: UNKNOWN
